{
  "items": [
    {
      "id": "7f244d1244129b6108007ae5",
      "title": "渡过高山和海洋，岁月就此流过在眼前",
      "summary": "前两天看了一眼博客，觉得不太对劲——我怎么就写了这么多经验贴？ 马上自己又给出答案：可能是活得有点长了吧。 这是不对的，我一个搞风花雪月的，怎么能写这么多经纶八股。",
      "image": null,
      "publishedAt": "2021-07-19T23:56:23Z",
      "sourceId": "88a1fc290dd0b8a7",
      "sourceTitle": "沉默之沙",
      "link": "https://yukieyun.net/nonsense/crossing-mountains-and-oceans/",
      "detailPath": "articles/7f244d1244129b6108007ae5.json"
    },
    {
      "id": "df0124d02653e722cfc364ae",
      "title": "基于 Vercel 和 MongoDB 的叨叨·改",
      "summary": "不再依赖于 Github issue, 增加了可用的前端页面来发送内容",
      "image": null,
      "publishedAt": "2021-07-18T21:16:30Z",
      "sourceId": "a3783910db542651",
      "sourceTitle": "极东魔术昼寝结社",
      "link": "https://blog.jaoushingan.com/2021/07/18/daodao-kai/",
      "detailPath": "articles/df0124d02653e722cfc364ae.json"
    },
    {
      "id": "02078ab81e69a2d259478271",
      "title": "二语习得理论+Duolingo自学葡萄牙语之一",
      "summary": "我想学习葡萄牙语的念头由来已久，具体可以追溯到2002年的日韩世界杯。中国队vs巴西队的那一场，李铁在球员握手时停下来和罗纳尔多说了一句话，罗纳尔多愣了一下，又回了他一句。这短短的几秒钟被国内体育媒体反复报道，催生多篇头条（放在今天就是一票10万+）。 在Mastodon上开了一个tag叫“葡语101”，和其他的101代指入门不同，我的101是指这已经是我第101次试图学习巴西葡萄牙语了（此处为夸张修辞，望周知）。 本次学习已坚持四周，四舍五入一个月，先小结一下；之二可能要等三个月或六个月的时候再写。",
      "image": null,
      "publishedAt": "2021-07-17T14:18:38Z",
      "sourceId": "88a1fc290dd0b8a7",
      "sourceTitle": "沉默之沙",
      "link": "https://yukieyun.net/takeaway/second-language-acquisition-duolingo-brazilian-portuguese-1/",
      "detailPath": "articles/02078ab81e69a2d259478271.json"
    },
    {
      "id": "a772650169b915854ee2ac2f",
      "title": "为 butterfly 主题的 twikoo 添加图片点击放大功能",
      "summary": "butterfly 把各种插件都集成好了, 真方便啊",
      "image": null,
      "publishedAt": "2021-07-16T01:09:38Z",
      "sourceId": "a3783910db542651",
      "sourceTitle": "极东魔术昼寝结社",
      "link": "https://blog.jaoushingan.com/2021/07/16/twikoo-img-zoom/",
      "detailPath": "articles/a772650169b915854ee2ac2f.json"
    },
    {
      "id": "6fe365abf1f352dd389d4af6",
      "title": "程序员可能必读书单推荐（一）",
      "summary": "",
      "image": null,
      "publishedAt": "2021-07-16T00:00:00Z",
      "sourceId": "4d49716051922902",
      "sourceTitle": "面向信仰编程 - Articles",
      "link": "https://draven.co//books-1",
      "detailPath": "articles/6fe365abf1f352dd389d4af6.json"
    },
    {
      "id": "e864e949991e6abd76bdea92",
      "title": "叁拾一周：No.3",
      "summary": "这是「叁拾一周」第三期，感谢这周新增的邮件订阅用户，目前订阅人数达到了 30 位。 很偶然的一个数字，我在微信里简单聊过自己在做这件事，初期订阅的用户是 12 位，上一期发完就暴涨 18 个人，我一度怀疑是某人推荐了我的通讯，如果是这样，可以邮件联系我（地址见文末），也许我们可以交个朋友，也许有什么地方我也可以帮助你。 上一期 刚刚聊到，对陌生人或者说网络世界中一个不认识的人，能先以信任待之，已经是 21 世纪新传统美德了。 本期聊一聊我在学开车时的一些收获，以及三个关键词：暂停、磨合和距离。 未来的车还需要开么？这是我观察未来的一个小视角，它的上一层是城市建设，下一层是当前最火热的自动驾驶，而母题则是人和人的互动。对于未来，我也在 Telegram 上建了一个频道 「未来生活手册」 ，希望能从里面提前感受到…",
      "image": null,
      "publishedAt": "2021-07-13T00:00:00Z",
      "sourceId": "fc41292f8a54624e",
      "sourceTitle": "Elizen's Blog",
      "link": "https://elizen.me/newsletter/2021/07/newsletter-003/",
      "detailPath": "articles/e864e949991e6abd76bdea92.json"
    },
    {
      "id": "2512af365ca24bb295d9b567",
      "title": "如何提高缓存系统的内存利用率和可扩展性 · NSDI '21",
      "summary": "",
      "image": null,
      "publishedAt": "2021-07-12T00:00:00Z",
      "sourceId": "4d49716051922902",
      "sourceTitle": "面向信仰编程 - Articles",
      "link": "https://draven.co//papers-segcache",
      "detailPath": "articles/2512af365ca24bb295d9b567.json"
    },
    {
      "id": "ee755a663b5e677d9a501e58",
      "title": "叁拾一周：No.2",
      "summary": "这本来是要发在微信公众号里的一篇文章，取名《近况》。开头是这么写的： 没封号，也没消失，其实最近输入还格外勤奋，但就像 无题 里说的，单纯是没什么可写的。输入的越多，提炼出来的东西越简单，要么三两句就讲清楚了，不值得写一篇文章，要么写就需要长篇大论，最好加上一定程度的辩论。索性就不写了。 按照以往惯例，聊天节目是我这里最火的，就聊聊近况好了。想到哪里说到哪里。 但写着写着，主题明确，也到了我心目中一篇通讯的体量，索性原封不动发出来，给大家做个参考。 本期聊的是我关于订阅邮件通讯的几点建议。 最近在写「不是 News，只有 Letter」的 「叁拾一周」 ，写了两期，间隔半年时间，恐怕第三期又会遥遥不可期 1 。 我一直想聊一聊 NewsLetter 这个东西，我认为它和播客一样，是一种很好的信息载体，要远好于…",
      "image": null,
      "publishedAt": "2021-07-08T00:00:00Z",
      "sourceId": "fc41292f8a54624e",
      "sourceTitle": "Elizen's Blog",
      "link": "https://elizen.me/newsletter/2021/07/newsletter-002/",
      "detailPath": "articles/ee755a663b5e677d9a501e58.json"
    },
    {
      "id": "c035eda2ab217ab3dc2c5b06",
      "title": "自动添加 twikoo 评论中的友链",
      "summary": "基于 twikoo 实现友链自动添加, 不再需要手动更新 link.yml. 后端使用最简化的 flask",
      "image": null,
      "publishedAt": "2021-07-06T02:38:38Z",
      "sourceId": "a3783910db542651",
      "sourceTitle": "极东魔术昼寝结社",
      "link": "https://blog.jaoushingan.com/2021/07/06/auto-update-link/",
      "detailPath": "articles/c035eda2ab217ab3dc2c5b06.json"
    },
    {
      "id": "eebd657d9a7780d15b226197",
      "title": "提高 LinkedIn Profile 质量，让 Recruiter 主动上门",
      "summary": "这篇文章最早也是发在豆瓣的，算是经受住了时间的考验，搬到博客存档。另外之前那篇《申请学校时如何利用LinkedIn获取有效信息》也有LinkedIn中国区的公众号运营联系授权转载，嘻嘻。 加拿大是众所周知的就业市场不活跃，我来的时候每个人都说要 networking，要内推，但我在这里基本没有同学和朋友，偶尔几个想帮忙也不在同一个行业。 我于是发挥自己以前研究SEO的心得，开始研究linkedin的搜索规则，包装到每周能收3-5封 recruiter 的邮件，每周都有面试。不多废话了，直接上优化流程，照着step by step做即可。【适用于美国包装！提炼精髓也适用于国内简历修改。对有几年经验的情况优化效果最好，对毕业生的效果有限，但思路可以留着以后用。",
      "image": null,
      "publishedAt": "2021-07-05T17:16:22Z",
      "sourceId": "88a1fc290dd0b8a7",
      "sourceTitle": "沉默之沙",
      "link": "https://yukieyun.net/takeaway/optimize-linkedin-profile/",
      "detailPath": "articles/eebd657d9a7780d15b226197.json"
    },
    {
      "id": "80e87970680e07f9c83e2a75",
      "title": "Talk about DAO 系列",
      "summary": "组织形态升级",
      "image": "https://res.wx.qq.com/a/wx_fed/assets/res/MjliNWVm.svg?t=75788f72-b81a-4379-a960-40067f92c66c",
      "publishedAt": "2021-07-02T00:00:00Z",
      "sourceId": "8b5512735fc2ab63",
      "sourceTitle": "NotionNext BLOG",
      "link": "https://github.com/noncegeek/article/dao",
      "detailPath": "articles/80e87970680e07f9c83e2a75.json"
    },
    {
      "id": "1bc281f1177f5307727a0f6e",
      "title": "Indie Hacker 成长指南系列",
      "summary": "独立开发者生命成长",
      "image": "https://res.wx.qq.com/a/wx_fed/assets/res/MjliNWVm.svg?t=5e0620b3-68d4-471c-a823-26cb3c9c65e1",
      "publishedAt": "2021-07-02T00:00:00Z",
      "sourceId": "8b5512735fc2ab63",
      "sourceTitle": "NotionNext BLOG",
      "link": "https://github.com/noncegeek/article/indiehacker",
      "detailPath": "articles/1bc281f1177f5307727a0f6e.json"
    },
    {
      "id": "74bd4ca83bab2b605fbda1b4",
      "title": "Move dApp 极速入门系列",
      "summary": "猛学 Move",
      "image": "https://res.wx.qq.com/a/wx_fed/assets/res/MjliNWVm.svg?t=34b1d951-a57e-4e85-806c-41d1a88dc5c3",
      "publishedAt": "2021-07-02T00:00:00Z",
      "sourceId": "8b5512735fc2ab63",
      "sourceTitle": "NotionNext BLOG",
      "link": "https://github.com/noncegeek/article/move",
      "detailPath": "articles/74bd4ca83bab2b605fbda1b4.json"
    },
    {
      "id": "096fcce26f898e8700cd2d0e",
      "title": "暴雨",
      "summary": "今天7月1日， 建党100周年，2021年下半年第一天。 暴输，暴雨，暴跌。 幸亏我不是一个迷信的人， 手有雨衣，户有余粮， 加油满仓。",
      "image": null,
      "publishedAt": "2021-07-01T00:00:00Z",
      "sourceId": "fc41292f8a54624e",
      "sourceTitle": "Elizen's Blog",
      "link": "https://elizen.me/posts/2021/07/2021-07-01/",
      "detailPath": "articles/096fcce26f898e8700cd2d0e.json"
    },
    {
      "id": "f9d76e1a58f89a57ec5b1cef",
      "title": "关于转码的非技术问题回答合集",
      "summary": "前面来一个防杠声明：我绝对支持任何人选择做自己想做的事，无论这件事是瞎逼还是发财，只要你愿意承受代价，YOUR LIFE, YOUR CHOICE! 所以，意志坚定思维强悍基本不被他人意见干扰人生的人（比如我），是不应该看下面的内容的。 要不要转是每个人自己的决定，但是不少人在做出最后决定时，用来作为论据的可能是一些流传很久的谬误。这篇文章只是澄清或者纠偏一些问题，避免部分人因为得到（我认为）的信息错误而做出错误的决定。",
      "image": null,
      "publishedAt": "2021-06-29T18:40:01Z",
      "sourceId": "88a1fc290dd0b8a7",
      "sourceTitle": "沉默之沙",
      "link": "https://yukieyun.net/takeaway/change-career-to-sde/",
      "detailPath": "articles/f9d76e1a58f89a57ec5b1cef.json"
    },
    {
      "id": "719ae558fb1c315fa4d42c4f",
      "title": "计算机网络 4 -网络层",
      "summary": "网络层的主要任务 实现网络互连 进而实现数据报再各网络之间的传输 要实现网络层任务, 需要解决以下的问题 网络层向运输层提供怎样的服务 可靠传输还是不可靠传输 网络寻址问题 路由选择问题 人工配置 实现路由选择协议",
      "image": null,
      "publishedAt": "2021-06-29T00:00:00Z",
      "sourceId": "a3783910db542651",
      "sourceTitle": "极东魔术昼寝结社",
      "link": "https://blog.jaoushingan.com/2021/06/29/%E8%AE%A1%E7%AE%97%E6%9C%BA%E7%BD%91%E7%BB%9C/%E8%AE%A1%E7%AE%97%E6%9C%BA%E7%BD%91%E7%BB%9C_04/",
      "detailPath": "articles/719ae558fb1c315fa4d42c4f.json"
    },
    {
      "id": "4532b36ab29a3de1c8089a8b",
      "title": "家书（2021）",
      "summary": "老爷子： 一切安好。 今年总算回去了，机票改了又改，赶在清明节看看你，看看家里。都好，勿念。但是时间紧任务重，总是很难安安静静聊一聊。索性，还是在信里讲。 小嘟嘟 2 岁多，整天活蹦乱跳，把人累得不行。去年信 里 我说他十五个月了，爱说两个字，一个是「疼」，一个是「好」，除此之外每天爸爸爸爸爸爸喊个不停。今年他厉害不少，中文英文的，混着说。中文我已经不太担心了，词汇，逻辑，组织语言，已经可以清楚、完整地表达自己的想法，是一个成熟的小家伙了。英文，他没有环境，但我有信心。有机会，要去多接触，多适应。 一方面，我惊讶于小朋友学习能力之强，我发现可以用交流的方式跟他讲述一些事情后，语言这项本能就发挥了不小作用。他经常给我一些意外，尤其是语言上的，因果、转折、递进、比喻、反问，张嘴就来。现在他喜欢火车、铁轨、大飞机，…",
      "image": null,
      "publishedAt": "2021-06-28T00:00:00Z",
      "sourceId": "fc41292f8a54624e",
      "sourceTitle": "Elizen's Blog",
      "link": "https://elizen.me/posts/2021/06/letter-for-family-2021/",
      "detailPath": "articles/4532b36ab29a3de1c8089a8b.json"
    },
    {
      "id": "10ff04b97dd4780a6f7612bf",
      "title": "申请学校时如何利用LinkedIn获取有效信息",
      "summary": "这篇文章最早发在豆瓣的women指西组，但该组转为私密组后很多没进组的人就看不到了。今天有姑娘私信跟我说之前看我在组里发的文章帮到她很多，希望我不要删帖——干脆找时间把之前写过的感觉还有用的帖子搬运到博客上，方便以后回答别人问题时甩链接。 从申请学校的角度，第一个信息获取渠道自然是学校的官网。学校官网里一般把 admission requirement ，学费和生活成本，申请时间线，学生基础信息等等都列得清清楚楚。根据这些信息搜集，缩小了目标范围后，另一个有效的工具就是 LinkedIn。",
      "image": null,
      "publishedAt": "2021-06-25T14:13:35Z",
      "sourceId": "88a1fc290dd0b8a7",
      "sourceTitle": "沉默之沙",
      "link": "https://yukieyun.net/takeaway/use-linkedin-efficiently/",
      "detailPath": "articles/10ff04b97dd4780a6f7612bf.json"
    },
    {
      "id": "da2afe1e7261677ae7391b87",
      "title": "将 mp4 视频切片成 ts 后使用 jsDelivr 加速制作 \"视频床\"",
      "summary": "薅资本主义的羊毛",
      "image": null,
      "publishedAt": "2021-06-25T00:00:00Z",
      "sourceId": "a3783910db542651",
      "sourceTitle": "极东魔术昼寝结社",
      "link": "https://blog.jaoushingan.com/2021/06/25/jsDelivr/%E8%96%85%E7%BE%8A%E6%AF%9B/",
      "detailPath": "articles/da2afe1e7261677ae7391b87.json"
    },
    {
      "id": "d1e4d3d6342f1aedf70254b8",
      "title": "Python 实现窗口保持置顶",
      "summary": "今天一边看视频一边用 Typora 记笔记的时候发现一个问题, Typora 自带的 保持窗口在最前端 不知何故会失效, 所以我就想用 Python 写一个可以让窗口强制指定的工具,",
      "image": null,
      "publishedAt": "2021-06-24T00:00:00Z",
      "sourceId": "a3783910db542651",
      "sourceTitle": "极东魔术昼寝结社",
      "link": "https://blog.jaoushingan.com/2021/06/24/tools/window-to-top/",
      "detailPath": "articles/d1e4d3d6342f1aedf70254b8.json"
    },
    {
      "id": "c7609be466ee2e036e8e2d03",
      "title": "两个德国演员",
      "summary": "Wikipedia上这短短的一段话，仿佛浓缩了的一段史诗。",
      "image": null,
      "publishedAt": "2021-06-20T01:32:24Z",
      "sourceId": "88a1fc290dd0b8a7",
      "sourceTitle": "沉默之沙",
      "link": "https://yukieyun.net/watching/two-german-actors/",
      "detailPath": "articles/c7609be466ee2e036e8e2d03.json"
    },
    {
      "id": "8e7b9d0690289cd2d93f6de5",
      "title": "Windows 10 下使用 MSVC 2019 编译 Nginx 64位过程记录",
      "summary": "前言 Nginx 在 Windows 下还是很实用的，可以作为前端的 HTTP 部署测试工具，或者当然可以用 Python 自带的 http.server 来部署，都挺快的。除了部署前端项目之外，放一些自制的基于 Web 的小工具都是极好的。 下载源码包 Nginx 源码 Nginx 在 Windows 下编译的源码与 Linux 下的不同，直接从官网的 download 里面下载是编译不过的，需要从下面的 Mercurial 链接下载，Mercurial 也是一种类似于 Git 的版本管理工具 下载地址: http://hg.nginx.org/nginx 注意，请选择一个带有 RELEASE TAG 的版本进行下载，如下图橙色方框所示 截至发文， Nginx 的最新 release 版本为 1.21.4…",
      "image": "https://cdn.taurusxin.com/old-cdn/typecho/2021/06/14/download.png",
      "publishedAt": "2021-06-16T23:56:00Z",
      "sourceId": "3220115c042340a7",
      "sourceTitle": "TaurusXin 的独立博客",
      "link": "https://www.taurusxin.com/nginx-windows-build/",
      "detailPath": "articles/8e7b9d0690289cd2d93f6de5.json"
    },
    {
      "id": "82d8542085048a067f395e1f",
      "title": "数据库设计",
      "summary": "",
      "image": null,
      "publishedAt": "2021-06-12T00:00:00Z",
      "sourceId": "a3783910db542651",
      "sourceTitle": "极东魔术昼寝结社",
      "link": "https://blog.jaoushingan.com/2021/06/12/%E6%95%B0%E6%8D%AE%E5%BA%93/database_design/",
      "detailPath": "articles/82d8542085048a067f395e1f.json"
    },
    {
      "id": "2b9e63fedde243c18e6770dc",
      "title": "叁拾一周：No.1",
      "summary": "好久不见。其实这是我的第二封信，上一封可以点击 这里 查看。一开始计划用 NewsLetter 的形式，最终决定去掉 News，只留 Letter。你也可以理解为，我只想写信，并不想说教。但这个过程从两封信的间隔可以看得出来，下定决心并不容易。甚至写与不写，也犹豫很久。 今天要说的话，和昨天想写的、已经选好的内容相差甚远，可以说毫不相关。 我要记录什么？ 周三好， 读库 《0901》 中唐诺 1 写了一篇《棋士》，聊羽生善治 2 。文章从日本将棋棋士羽生善治 开始 ，「历数将棋与围棋、国际象棋等的异同，又从当代顶尖棋士的进步差距谈到“物竞天”的生物学法则，以建筑物的“巴比塔”迷思谈到进化的上限，再从对棋入迷的心理谈到人们自主学习的心理，再由此谈到眼高手低的“欣赏”与“实干”之间的差距……读的时候只觉得字字珠玑…",
      "image": null,
      "publishedAt": "2021-06-09T00:00:00Z",
      "sourceId": "fc41292f8a54624e",
      "sourceTitle": "Elizen's Blog",
      "link": "https://elizen.me/newsletter/2021/06/newsletter-002/",
      "detailPath": "articles/2b9e63fedde243c18e6770dc.json"
    },
    {
      "id": "fa1e443bce8bb660fce795e7",
      "title": "Apple Music 杜比全景声 / 无损音乐赏析指南",
      "summary": "前言 北京时间 2021 年 5 月 17 日，苹果正式宣布 Apple Music 将推出杜比全景声与无损音乐的支持，并且是全曲库的支持，今天（6月8日）已经有部分用户的设备已经支持了，我的设备也第一时间支持了。 Apple 官方网站传送门 开启功能 首先，需要将 iPhone 或者 iPad 的系统版本升级到 iOS / iPadOS 14.6以上 体验之前，需先手动开启功能，Apple 没有默认开启的原因是可能会为用户带来额外的网络流量开销。 在 iOS 或者 iPadOS 中，进入 设置 - 音乐 - 就可以看到两个新的选项 进入杜比全景声选项，即可选择自动或是始终打开 在音频质量中，若是选中了高解析无损，将会支持到 Apple 自家的 ALAC 无损音频编码，且最高 24位 / 192kHz 的音频…",
      "image": "https://cdn.taurusxin.com/old-cdn/typecho/2021/06/08/new-options.jpeg",
      "publishedAt": "2021-06-08T23:10:00Z",
      "sourceId": "3220115c042340a7",
      "sourceTitle": "TaurusXin 的独立博客",
      "link": "https://www.taurusxin.com/2021applemusic2/",
      "detailPath": "articles/fa1e443bce8bb660fce795e7.json"
    },
    {
      "id": "4d46da8d701bc7f736cd2dd7",
      "title": "Mastodon媒体库迁移：从Scaleway到AWS S3",
      "summary": "本次将Mastodon的媒体库从Scaleway的云存储迁移到AWS的S3的记录；最后也简述了在安装Mastodon后直接使用AWS的S3的方法。 免责声明： 1. 本文不是一个step by step的指导，可能有疏漏，对可能造成的损失概不负责；建议使用前反复阅读文中提到的其他指南文章和文档（写得比本文详尽且负责），在了解原理后再行操作。 2. 本文的重点在于其他迁移指南里没有提到的AWS S3的使用和可能遇到的问题。",
      "image": null,
      "publishedAt": "2021-06-06T01:35:59Z",
      "sourceId": "88a1fc290dd0b8a7",
      "sourceTitle": "沉默之沙",
      "link": "https://yukieyun.net/tech/mastodon-media-from-scaleway-to-aws-s3/",
      "detailPath": "articles/4d46da8d701bc7f736cd2dd7.json"
    },
    {
      "id": "157f2c61ee1b0942a18c0e24",
      "title": "参与了一期播客讨论不婚不育这件事",
      "summary": "起因是穿堂风老师在豆瓣征集这个话题的嘉宾，且希望是决定已经做了比较多年，不太可能会反悔（直白一点说就是再过几年就绝经啦）的人。 我去参加这期节目的动机是，这些年来断断续续有人问，说多不多说少不少，来来回回都是那些问题：你为什么不结婚，你是不是感情受过什么伤害，你怎么说服父母，你一个人过日子不怕孤独吗，你养老怎么办……极少数有恶意的就直接拉黑了，大多数是好奇，又或者希望从你这里得到一点对抗的经验，但每次都要论述一遍也很烦。想过单独写篇博客说这个事，这样有人问就塞链接，但我又懒得很。 感谢穿堂风老师整理了这么齐全的问题，一次讲完，以后再有人问，就可以塞链接了^_^",
      "image": null,
      "publishedAt": "2021-06-03T16:22:49Z",
      "sourceId": "88a1fc290dd0b8a7",
      "sourceTitle": "沉默之沙",
      "link": "https://yukieyun.net/takeaway/single-life/",
      "detailPath": "articles/157f2c61ee1b0942a18c0e24.json"
    },
    {
      "id": "28c1bcc2ea2478c15d988ff1",
      "title": "鸿蒙 OS，道阻且长",
      "summary": "华为昨天发布的 鸿蒙 OS 非常牛，非常棒，非常好，重要的是，非常对。 我一直有个业内偏见，家居里的互联，所谓智能家居，智慧家庭，都是伪命题，伪需求。你家的冰箱和你家的洗衣机有什么可互联互通的。但是手机、电脑、电视、手表、音箱、车，VR/AR，这些就不一样了。它们可以和一切互联，互联一切。路上的红绿灯、广告牌、随处可见的显示屏，随处都看不见的传感器。 最后，这些东西就会变成你的娱乐管家，管理你的阅读、新闻、影音；你的健康管家，管理你的身体状况；直到成为你的家庭管家，管理你的社交、计划、旅行，每日生活。 但是，这些东西，苹果也在做，而且苹果的打法一向是深挖洞，广积粮，缓称王。技术储备非常深。更重要的是，库克之所以接班，很大的一个原因是他在苹果做的供应链管理非常厉害。 真的想成，炫酷的效果，深厚的技术都没办法单打…",
      "image": null,
      "publishedAt": "2021-06-03T00:00:00Z",
      "sourceId": "fc41292f8a54624e",
      "sourceTitle": "Elizen's Blog",
      "link": "https://elizen.me/posts/2021/06/harmonyos/",
      "detailPath": "articles/28c1bcc2ea2478c15d988ff1.json"
    },
    {
      "id": "b06535ac97c3f5980783b132",
      "title": "拿破仑和约瑟芬",
      "summary": "他之所以在后来的岁月里强调他对约瑟芬的爱，一定意义上是因为，和约瑟芬离婚反映了他not strong enough，和需要继承人相比，他还需要和其他国家的联盟（所以他考虑和俄国或奥地利联姻）。尽管约瑟芬也在他的政治崛起中起了一些帮助作用，但和约瑟芬结婚时他并没有想那么多，约瑟芬是他“自主选择”的象征。对约瑟芬的所有慷慨都是他权力的体现，约瑟芬的家族的崛起就是他的崛起（约瑟芬的一对儿女都比较优秀也是因素之一）。",
      "image": null,
      "publishedAt": "2021-05-30T02:55:29Z",
      "sourceId": "88a1fc290dd0b8a7",
      "sourceTitle": "沉默之沙",
      "link": "https://yukieyun.net/reading/napoleon-bonaparte-and-josephine/",
      "detailPath": "articles/b06535ac97c3f5980783b132.json"
    },
    {
      "id": "230d5e2defdb179ce14c8501",
      "title": "「项目实战」校园微信小程序 03.后端技术",
      "summary": "数据库 后端最离不开的就是和数据库打交道，果断选用开源的 MySQL 社区版作为本次项目的数据库服务。 MySQL版本为 10.3.23-MariaDB ，地域为腾讯云香港云数据库 建表 刚开始建表使用的都是默认参数，其中用户表中包含用户的微信昵称，好在我们有好几个测试用的微信号，发现了其中一个的问题所在。 MySQL默认建表的字符排序规则为 utf8-unicode-ci，就会导致微信用户名中带有4字节的 emoji 字符无法写入数据库，从而报错。 解决方案就是更改为utf8mb4，该排序规则支持单字符四字节宽度的 emoji 字符。 为了统一，所有字符串都采用这个排序规则。 Web服务框架 因为是小项目，直接使用 Flask 一把梭。 PS：去年底开始，Python 有个叫 fastapi 的框架火了起来…",
      "image": "https://cdn.taurusxin.com/old-cdn/typecho/2021/05/26/utf8-unicode.png",
      "publishedAt": "2021-05-26T15:55:00Z",
      "sourceId": "3220115c042340a7",
      "sourceTitle": "TaurusXin 的独立博客",
      "link": "https://www.taurusxin.com/yiyu-backend/",
      "detailPath": "articles/230d5e2defdb179ce14c8501.json"
    },
    {
      "id": "acf1209b84f495406e409f69",
      "title": "第三帝国的兴亡 by William L. Shirer",
      "summary": "这套书看完有快一个月了，恰好这个月各种事繁杂无序，拖到现在才能把总结写一下。但在血淋淋的历史面前，又实在不知道说什么。感觉第三帝国仿佛一个经典历史剧本，在不同的时间，在不同的地点，反复翻拍。如果抽离第二次世界大战带给整个世界的苦难的话，甚至可以当做一个荒诞笑话合集来看。 二战时受害最惨烈的几个地方，如今依旧深陷极左or极右的泥潭。如果说人类从二战中汲取了什么教训，那就是——希特勒那一套民粹煽动还挺tm管用的呢。二战以极其酷烈的方式震慑住了大国们，让大家在之后的几十年里稍微谨慎了一些，不敢轻易开启战端——但这个震慑眼看着似乎也快到期了。",
      "image": null,
      "publishedAt": "2021-05-26T01:48:26Z",
      "sourceId": "88a1fc290dd0b8a7",
      "sourceTitle": "沉默之沙",
      "link": "https://yukieyun.net/reading/the-rise-and-fall-of-the-third-reich/",
      "detailPath": "articles/acf1209b84f495406e409f69.json"
    },
    {
      "id": "6d4faea3bb3224401e27e23c",
      "title": "广告",
      "summary": "上一篇 《去世》 不知道得罪了哪个夺命阎王，也跟着去世了。微信后台说，违反了相关法律法规，我实在不能理解，也是出于好奇，就提了个申诉，想知道哪里违反，又违反了哪里？ 确实，上一篇文章阅读量不低，当然，是拿我这小破庙日常的香火来比。结尾也发了一点牢骚，写了一点感想。本来想靠着这里实现买书财务自由，但也无奈。一来，买书的节奏不好把握，几个月不买，一个月买几次，都时有发生；二来，一个月写几篇，一篇赚多少香火钱，也没个准头，至于哪篇看的人多些，哪篇少些，我确实不会运营；第三，因为阅读上的感受，我还是把文中广告关了，底部的，需要靠点击才有可观收入，也相当于自断一半出路。 不过要说我写公众号胸无大志，也不是。写到今天，流量是不可能的，出书我不敢讲，心里还有点儿念头，毕竟还有些密而不发的未完成草稿攥在手里。但这都是后话，也…",
      "image": "https://static.elizen.me/img/2021-05-26-010142.jpg",
      "publishedAt": "2021-05-26T00:00:00Z",
      "sourceId": "fc41292f8a54624e",
      "sourceTitle": "Elizen's Blog",
      "link": "https://elizen.me/posts/2021/05/letters-of-photo/",
      "detailPath": "articles/6d4faea3bb3224401e27e23c.json"
    },
    {
      "id": "edbd70f15cfe8daa1f544e84",
      "title": "去世",
      "summary": "左晖去世。链家网创始人。 朋友圈都在转他生前著名的一句话，做难而正确的事。去年恰好出了一本关于他的书《详谈：左晖》，很多人拿出来读。 我不了解他，但看起来是个不错的企业家，链家我还算熟悉，这几年看房、买房、卖房，没少打交道，但自从他弄了个贝壳 APP，一定要把数据指标量化，指导大家怎么买怎么卖，我就有点儿意见了。在我看，买卖这个东西，根子上是信任，信任这个东西，要回到人身上。房子买卖，在中国是个大事，不管几线城市，都是拿出了不小一笔家庭开支，来购买一个固定住所，这东西就像相亲，总归是得看上了眼儿，才能往下聊，熟悉了之后，优点缺点自己衡量，觉得值就下手，不值那就拜拜。 很多人还在传一句话，可能是链家内部的某种文化，聚是一团火，散是满天星。话不错，但非要把星星弄成火，就没意思了。 袁隆平去世。 值得国葬吧。但要说…",
      "image": null,
      "publishedAt": "2021-05-24T00:00:00Z",
      "sourceId": "fc41292f8a54624e",
      "sourceTitle": "Elizen's Blog",
      "link": "https://elizen.me/posts/2021/05/death/",
      "detailPath": "articles/edbd70f15cfe8daa1f544e84.json"
    },
    {
      "id": "c32b12d03ec82e2e16567026",
      "title": "【区块链】Dogecoin 狗狗币挖矿教程",
      "summary": "最近一段时间狗狗币很火，价格暴涨。狗狗币挖矿其实很简单，只需要下载一个狗狗币钱包，然后下载一个挖矿程序，配置一下钱包地址，就可以开始挖了。 更新说明 （更新于2024年3月27日）这篇文章第一次写于2021年5月，已经过去了很久。由于最近这篇文章的关注度比较高，这里针对一些问题进行更新。 首先连不上矿池的问题，这个问题可能是矿池的问题，也可能是网络问题，可使用 Clash的 TUN 模式 或者 Proxifier 等软件可将挖矿软件走全局代理，不是那个系统的全局代理，因为挖矿软件不遵循系统代理。 其次是挖矿没有算力的，这个问题首先尝试更新你的显卡驱动，不要使用特别旧的版本，另外可以自行尝试一些其它的算法，比如新出的 EthashB3 等，可以拉到底下看新的算法教程，或者点 这里 。 在点进矿池首页，会有很多算…",
      "image": "https://cdn.taurusxin.com/hugo/2024/03/27/unmineable-index.png",
      "publishedAt": "2021-05-21T10:57:00Z",
      "sourceId": "3220115c042340a7",
      "sourceTitle": "TaurusXin 的独立博客",
      "link": "https://www.taurusxin.com/doge-mining/",
      "detailPath": "articles/c32b12d03ec82e2e16567026.json"
    },
    {
      "id": "5c49bb6ba7c0807851e33dc1",
      "title": "无题",
      "summary": "有时候观察公众号也很有趣，不写订阅数量涨，写则跌。很多号都这样。 最近我也没写，说实话，就是没什么可写的。自从有了娃，生活单调至极，同时丰富至极。现在九成以上的空闲时间都在带娃，就这一件事，你说单调不单调，丰富呢，就是怎么带，在家玩什么，出门去哪里，每天变着花样陪他，或者说变着花样让他陪我。 很多地方以前不想去，懒得去，觉得麻烦，现在说走就走，也不含糊，含糊也没用，他在旁边嗷嗷叫，我要出去玩，我要出去玩，那既然答应了，总得做到吧，收拾箱子，背上书包，随时出发。跟他谈不了借口，借口没用，他不听，也听不懂，听懂了也听不进去，反正想去哪里，就一句话，我要去，任你雨打风吹，我自岿然不动。 书也没时间看，电影院就甭提了，这样反而乐得清闲，新闻也不看了，重要的落不下，不重要的没必要关心。反倒把精力都省下了。干什么不是干，…",
      "image": null,
      "publishedAt": "2021-05-18T00:00:00Z",
      "sourceId": "fc41292f8a54624e",
      "sourceTitle": "Elizen's Blog",
      "link": "https://elizen.me/posts/2021/05/wu-ti/",
      "detailPath": "articles/5c49bb6ba7c0807851e33dc1.json"
    },
    {
      "id": "c76596ced60f634a5cb38d5a",
      "title": "爱死机，爱发电",
      "summary": "虽然，我还没看，就发现网上各种喷，豆瓣 评分 也落到 7 分上下，但是就算新一季再垃圾，也比大部分国产电影好吧？ 而且，我还发现了一个小现象，豆瓣电影，7.5 分上下的作品，其实是最好看，看起来最舒服的。",
      "image": null,
      "publishedAt": "2021-05-17T00:00:00Z",
      "sourceId": "fc41292f8a54624e",
      "sourceTitle": "Elizen's Blog",
      "link": "https://elizen.me/posts/2021/05/love-death-robots/",
      "detailPath": "articles/c76596ced60f634a5cb38d5a.json"
    },
    {
      "id": "04460779be236ba421e527e6",
      "title": "多伦多半日游之Little Italy",
      "summary": "本周六我又双叒叕出来逛大街了。考虑到前几次走两个地方后都累成傻逼，今天只选择了一个目的地：Little Italy。 小意大利的形状是一个略趋近于正方形的长方形，最北是Harbord Street，最南是Dundas Street，西边到Ossington Avenue，东边到Bathurst Street。它在Dundas Street这里有一段和小葡萄牙（Little Portugal）是相邻的。 这个街区的中心是中间东西走向的College Street，沿街有许多意大利餐厅和酒吧。在这里居住的意大利裔，他们的祖上大多是一战期间从欧洲移居到加拿大的（小葡萄牙和小希腊的基本也是这么个情况）。",
      "image": null,
      "publishedAt": "2021-05-16T03:35:14Z",
      "sourceId": "88a1fc290dd0b8a7",
      "sourceTitle": "沉默之沙",
      "link": "https://yukieyun.net/roam/toronto-little-italy/",
      "detailPath": "articles/04460779be236ba421e527e6.json"
    },
    {
      "id": "f3903e547b1e5408872bb9b8",
      "title": "大宕机过后的得与失",
      "summary": "正是因为有过暴风雨的记忆，才会惊觉，如今这份早已熟识的平静，是多么的难能可得。",
      "image": null,
      "publishedAt": "2021-05-15T09:34:16Z",
      "sourceId": "06aa2ffd92b9d263",
      "sourceTitle": "糖菓·部落",
      "link": "https://candinya.com/posts/loss-and-lessons-after-a-major-downtime/",
      "detailPath": "articles/f3903e547b1e5408872bb9b8.json"
    },
    {
      "id": "e0aa8572155e16f7b926b47c",
      "title": "问题永远不能解决",
      "summary": "问题永远都不能解决，只是用一个更大的问题来掩饰当下的问题。 所以，历史是复杂的，不能从单一角度去看，去整理，去借鉴，可历史足够复杂，不做简化，只能深陷泥潭，把自己也埋进去。 所以，去看过往取得一定成就的人，他们采用了一个折中的变通的办法，建立模型。面对极度复杂的现实世界，他们明白，不能单一角度看，也不能全盘无遗漏地看，筛选关键词，以某些准则指导自己的决策，不断更新自己的关键词，更新自己的模型。是最现实同时最有成效的办法。 所以，他们解决不了的问题，他们就制造一个更大的问题。 这，就是现实世界。",
      "image": null,
      "publishedAt": "2021-05-12T00:00:00Z",
      "sourceId": "fc41292f8a54624e",
      "sourceTitle": "Elizen's Blog",
      "link": "https://elizen.me/posts/2021/05/problem-is-problem/",
      "detailPath": "articles/e0aa8572155e16f7b926b47c.json"
    },
    {
      "id": "94712b3619e7d34220e266c2",
      "title": "分享各类电子书（政治、IT、科普、历史、等，97本）",
      "summary": "插播一条消息： 4月22日，俺在前一篇博文回复读者评论。当时有人建议俺：把博客的评论都导入 Github。然后俺回了一条留言（ 链接 ）告诉对方：已经有热心网友干了这事儿。并且俺还贴出 Github 已有的某个仓库的网址（该仓库的作者会把博客新增的留言【实时同步】到 Github，已经运作了好几年） 大伙儿猜猜看，出了啥事儿？ 一星期之后，该仓库的作者在俺博客留言（ 链接 ），说他的仓库刚刚被 Github 封杀，连这个仓库对应的用户帐号都被禁掉（相当于【炸号】）。据说是有人向 Github 官方恶意投诉。 对 Github 社区比较熟悉的网友，请帮这位读者想点办法。 针对这事儿，俺补充说几点： 1. 很显然，有朝廷的走狗在俺博客长期蹲点，关注俺发的每一篇博文，每一条留言； 2. （十多年来）朝廷始终搞不定俺…",
      "image": null,
      "publishedAt": "2021-05-09T15:43:00Z",
      "sourceId": "92a77bfacd821259",
      "sourceTitle": "编程随想的博客",
      "link": "https://program-think.blogspot.com/2021/05/share-books.html",
      "detailPath": "articles/94712b3619e7d34220e266c2.json"
    },
    {
      "id": "bb88a3eb80cf10ed783cd398",
      "title": "多伦多半日游之Queen West和Little Portugal",
      "summary": "最近比较密集地暴走多伦多各街区，主要是因为在杭州住了10年，但连西湖都没逛过几次，也很少进城，基本蜗居三墩镇，以至于要离开时才发现好多地方都没去玩过。 所以……尽管还不知道什么时候能浪到下一个城市，还是趁着最近天气好到处多逛逛。 本周敲定的目的地是Queen Street West和Little Portugal。Queen West主要以时尚艺术出名，Little Portugal看名字就知道是过去的葡萄牙移民聚居区。今天其实没有把Queen West走到底，而是在接近Little Portugal的地方就往北拐，贯穿Little Portugal一直逛到Dundas West上。",
      "image": null,
      "publishedAt": "2021-05-09T00:28:31Z",
      "sourceId": "88a1fc290dd0b8a7",
      "sourceTitle": "沉默之沙",
      "link": "https://yukieyun.net/roam/toronto-queen-west-little-portugal/",
      "detailPath": "articles/bb88a3eb80cf10ed783cd398.json"
    },
    {
      "id": "98a7878735e44cb0699d0b3f",
      "title": "得到电子书试用体验（5月31日更新）",
      "summary": "开箱即用，只对自己负责的测评。（未完待续） 5月31日更新 其实跟电子书关系不大，发现得到有个大坑啊，我正在读的一本书阅读器上下载到本地了，还是可以读，但是打开网页版发现它下架了，现在搞得笔记没有办法导出，而且我也不知道（也不敢尝试）如果我联网了，阅读器上的本地书籍会不会同步给我干掉。 之前 Kindle 上买的书也有联网更新（其实就是删减部分片段）的情况出现，不知道得到怎么处理和解决。 感觉买硬盘最靠谱，也应了那句老话，数据还是放在自己手里最安全。 5月8日更新 最近一段时间一直在深度使用中，又有几个点值得聊一下。先说缺点： 第一，电容笔到了，马上拿起来划线，误触率极高，它既然做到 7.8 寸的大小， 就应该想到误触率的问题，目前我几乎没办法把手压在屏幕上划线，只要碰到，就会触发翻页。之前用过 Pad，虽然…",
      "image": null,
      "publishedAt": "2021-05-08T00:00:00Z",
      "sourceId": "fc41292f8a54624e",
      "sourceTitle": "Elizen's Blog",
      "link": "https://elizen.me/posts/2021/05/de-dao/",
      "detailPath": "articles/98a7878735e44cb0699d0b3f.json"
    },
    {
      "id": "f3a685ffc7ff6dfe911a79f8",
      "title": "逻辑和无逻辑",
      "summary": "《考纲》「要求考生克服紧张情绪，以平和的心态参加考试，合理支配考试时间，以实事求是的科学态度解答试题，树立战胜困难的信心，体现锲而不舍的精神」。",
      "image": null,
      "publishedAt": "2021-05-07T21:29:23Z",
      "sourceId": "4f3f8eb9d72c3840",
      "sourceTitle": "新世界的大门",
      "link": "https://blog.xinshijiededa.men/logical-or-not/",
      "detailPath": "articles/f3a685ffc7ff6dfe911a79f8.json"
    },
    {
      "id": "bdaa860ed0c63d30fd1352af",
      "title": "多伦多半日游之Degrassi St和Greektown",
      "summary": "想要去这条街看看的起源是这样的，在Mastodon的时间线上看到有人发一个视频片段，内容是高中生的修罗场。男生Declan想追回前女友Holli J，但Holli J此时已有另外的男友。Declan的妹妹和Holli J是好朋友，于是装酗酒让Holli J送自己回家，为哥哥争取一个旧情复燃的机会。Holli J一时难以决断如此复杂的感情关系，但在她明确say no后Declan仍执意吻她，Holli J因为对Declan仍有感情，于是在Declan的坚持下二人发生了关系。 这个片段让无数Declan和Holli J的cp粉对Declan脱粉，认为他的行为是rape。我考虑了一下这段视频放微博上会得到什么样的评论……Youtube继续给我推荐了电视剧全片，名叫Degrassi，是加拿大电视剧史上拍摄时间最长的电…",
      "image": null,
      "publishedAt": "2021-05-02T20:53:23Z",
      "sourceId": "88a1fc290dd0b8a7",
      "sourceTitle": "沉默之沙",
      "link": "https://yukieyun.net/roam/toronto-degrassi-st-greek-town/",
      "detailPath": "articles/bdaa860ed0c63d30fd1352af.json"
    },
    {
      "id": "3f112a7c27441ec0fe38c28c",
      "title": "计算机网络 1 -因特网概述",
      "summary": "因特网概述 网络、互连（联）网和因特网 网络是由若干结点和连接这些结点的链路组成的多个网络可以通过路由器互连起来, 构成一个覆盖范围更大的网络, 即互联网",
      "image": null,
      "publishedAt": "2021-05-02T00:00:00Z",
      "sourceId": "a3783910db542651",
      "sourceTitle": "极东魔术昼寝结社",
      "link": "https://blog.jaoushingan.com/2021/05/02/%E8%AE%A1%E7%AE%97%E6%9C%BA%E7%BD%91%E7%BB%9C/%E8%AE%A1%E7%AE%97%E6%9C%BA%E7%BD%91%E7%BB%9C_01/",
      "detailPath": "articles/3f112a7c27441ec0fe38c28c.json"
    },
    {
      "id": "a92fc6a1ab7bdfa5979b71fd",
      "title": "计算机网络 2 -物理层",
      "summary": "物理层的基本概念 物理层所考虑的 怎样在连接各种计算机的传输媒体上传输比特流 物理层为数据链路层屏蔽了各种传输媒体的差异, 是数据链路层只需要考虑如何完成本层的",
      "image": null,
      "publishedAt": "2021-05-02T00:00:00Z",
      "sourceId": "a3783910db542651",
      "sourceTitle": "极东魔术昼寝结社",
      "link": "https://blog.jaoushingan.com/2021/05/02/%E8%AE%A1%E7%AE%97%E6%9C%BA%E7%BD%91%E7%BB%9C/%E8%AE%A1%E7%AE%97%E6%9C%BA%E7%BD%91%E7%BB%9C_02/",
      "detailPath": "articles/a92fc6a1ab7bdfa5979b71fd.json"
    },
    {
      "id": "d340c98b2942d0bdfc21b7be",
      "title": "计算机网络 3 -数据链路层",
      "summary": "数据链路层 数据链路层概述 数据链路层在网络体系中所处的地位研究数据链路层的问题时, 可以认为数据包只在数据链路层沿水平方向传送.如下图, 两台主机之间的通信可以看作是在 4 条不同的链路上的通信组成的.",
      "image": null,
      "publishedAt": "2021-05-02T00:00:00Z",
      "sourceId": "a3783910db542651",
      "sourceTitle": "极东魔术昼寝结社",
      "link": "https://blog.jaoushingan.com/2021/05/02/%E8%AE%A1%E7%AE%97%E6%9C%BA%E7%BD%91%E7%BB%9C/%E8%AE%A1%E7%AE%97%E6%9C%BA%E7%BD%91%E7%BB%9C_03/",
      "detailPath": "articles/d340c98b2942d0bdfc21b7be.json"
    },
    {
      "id": "bbfa081657484fba1c146305",
      "title": "检测Magisk与Xposed",
      "summary": "不久前，开发者Rikka & vvb2060上架了一款环境检测应用 Momo ，把大家一直以来信任的各种反检测手段击得粉碎。下面我会通过部分已公开的源码，分析这个可能是史上最强的环境检测应用。",
      "image": null,
      "publishedAt": "2021-05-01T05:23:44Z",
      "sourceId": "511f3e9d589e2612",
      "sourceTitle": "残页的小博客",
      "link": "https://blog.canyie.top/2021/05/01/anti-magisk-xposed/",
      "detailPath": "articles/bbfa081657484fba1c146305.json"
    },
    {
      "id": "6a29e37102b530152e67b56c",
      "title": "「项目实战」校园微信小程序 02.前端技术",
      "summary": "自白 首先，这系列鸽了挺久的，最近也确实学业的问题，因为最近要操办出国的签证手续、学费，各种事项，自己都很久没上博客了，在此以表歉意！ 技术栈 首先就是技术栈选择，看我博客的人应该大多数都是比我强很多的大佬， 我的博客也只是作为学习经历的日志，并不能作为教程或是参考 ，还请各位前辈指点。因为这一次的工期较紧，我们直接选择了uniapp作为小程序的前端框架开发。 uni-app uniapp这个东西，说强也强，夸了这么多端，说拉胯也拉胯，包括IDE的bug奇多，UI框架bug等。 具体不多说了，百度都能找得到相关介绍。 uniapp最方便的就是用的 Vue 技术栈，mvvm 的思想在近几年的前端中很流行，前端三大框架 Vue / React / Augular。在App开发中，双向绑定数据流极大提升效率。 实际…",
      "image": "https://cdn.taurusxin.com/old-cdn/typecho/2021/05/07/uniapp.png",
      "publishedAt": "2021-04-27T16:36:00Z",
      "sourceId": "3220115c042340a7",
      "sourceTitle": "TaurusXin 的独立博客",
      "link": "https://www.taurusxin.com/yiyu-frontend/",
      "detailPath": "articles/6a29e37102b530152e67b56c.json"
    },
    {
      "id": "d5dce89bf9c0beec881f72b9",
      "title": "每周转载：从“肿瘤黑幕”看天朝的“医患矛盾”（网文8篇以及俺的点评）",
      "summary": "前一篇博文的评论区，俺回复了好几轮，显著超出以往。主要是因为，有几位热心读者写了很多条质量不错的留言，而且讨论很热烈。既然大伙儿捧场，俺当然也要有所表示。在此，向这几位热心读者表示感谢！ ★引子 前几天，关于“癌症治疗 ＆ 医患矛盾”的话题再次成为天朝舆论的热点，相关话题连续多日停留在“热搜排行版”。俺借此机会发一篇《每周转载》，分享相关报道，顺便抹黑一下党国。 如果俺转贴的这些报道，你都已经看过，可以直接跳到最后一个章节（俺写了比较长的一段点评）。 ★（北医三院肿瘤内科）张煜医生的爆料 4月18日，北医三院肿瘤内科的张煜医生在知乎发了一篇长文《写给我挚爱的国家和众多的肿瘤患者及家属——请与我一起呼吁，请求国家早日设立医疗红线，遏制肿瘤治疗中的不良医疗行为》。这篇长文立即引起轰动。 但是张煜医生当天晚上又把那…",
      "image": "https://lh5.googleusercontent.com/mZZunSh5dCEtA4HQg5DaH0zsqNT8eFZsLF6jenb3CWy04-httSxLCKL_YSevg0ozSqShxkSJ5_H8UNr6TWC4j-3-pUqxSROkS_qTBEJFi77aiinNm9USHqbCl8m283Kk2GsYZNVGdk4=s72-c",
      "publishedAt": "2021-04-25T14:25:00Z",
      "sourceId": "92a77bfacd821259",
      "sourceTitle": "编程随想的博客",
      "link": "https://program-think.blogspot.com/2021/04/weekly-share-152.html",
      "detailPath": "articles/d5dce89bf9c0beec881f72b9.json"
    },
    {
      "id": "9e663a30ab7899ffa8191222",
      "title": "Android Systrace 流畅性实战 3 ：卡顿分析过程中的一些疑问",
      "summary": "不同的人对流畅性(卡顿掉帧)有不同的理解，对卡顿阈值也有不同的感知，所以有必要在开始这个系列文章之前，先把涉及到的内容说清楚，防止出现不同的理解，也方便大家带着问题去看这几篇问题，下面是一些基本的说明 对手机用户来说，卡顿包含了很多场景，比如在 滑动列表的时候掉帧 、 应用启动白屏过长 、 点击电源键亮屏慢 、 界面操作没有反应然后闪退 、 点击图标没有响应 、 窗口动画不连贯、滑动不跟手、重启手机进入桌面卡顿 等场景，这些场景跟我们开发人员所理解的卡顿还有点不一样，开发人员会更加细分去分析这些问题，这是开发人员和用户之间的一个认知差异，这一点在处理用户(或者测试人员)的问题反馈的时候尤其需要注意 对开发人员来说，上面的场景包括了 流畅度 （滑动列表的时候掉帧、窗口动画不连贯、重启手机进入桌面卡顿）、 响应速…",
      "image": null,
      "publishedAt": "2021-04-24T11:55:12Z",
      "sourceId": "1aa1837ca33d8d55",
      "sourceTitle": "Android Performance",
      "link": "https://androidperformance.com/2021/04/24/android-systrace-smooth-in-action-3/",
      "detailPath": "articles/9e663a30ab7899ffa8191222.json"
    },
    {
      "id": "ee0aa8492ab5bdbebf247346",
      "title": "Android Systrace 流畅性实战 2 ：案例分析 - MIUI 桌面滑动卡顿分析",
      "summary": "不同的人对流畅性(卡顿掉帧)有不同的理解，对卡顿阈值也有不同的感知，所以有必要在开始这个系列文章之前，先把涉及到的内容说清楚，防止出现不同的理解，也方便大家带着问题去看这几篇问题，下面是一些基本的说明 对手机用户来说，卡顿包含了很多场景，比如在 滑动列表的时候掉帧 、 应用启动白屏过长 、 点击电源键亮屏慢 、 界面操作没有反应然后闪退 、 点击图标没有响应 、 窗口动画不连贯、滑动不跟手、重启手机进入桌面卡顿 等场景，这些场景跟我们开发人员所理解的卡顿还有点不一样，开发人员会更加细分去分析这些问题，这是开发人员和用户之间的一个认知差异，这一点在处理用户(或者测试人员)的问题反馈的时候尤其需要注意 对开发人员来说，上面的场景包括了 流畅度 （滑动列表的时候掉帧、窗口动画不连贯、重启手机进入桌面卡顿）、 响应速…",
      "image": null,
      "publishedAt": "2021-04-24T11:55:07Z",
      "sourceId": "1aa1837ca33d8d55",
      "sourceTitle": "Android Performance",
      "link": "https://androidperformance.com/2021/04/24/android-systrace-smooth-in-action-2/",
      "detailPath": "articles/ee0aa8492ab5bdbebf247346.json"
    },
    {
      "id": "9fc20dd0d410c46aa5dee29b",
      "title": "Android Systrace 流畅性实战 1 ：了解卡顿原理",
      "summary": "不同的人对流畅性(卡顿掉帧)有不同的理解，对卡顿阈值也有不同的感知，所以有必要在开始这个系列文章之前，先把涉及到的内容说清楚，防止出现不同的理解，也方便大家带着问题去看这几篇问题，下面是一些基本的说明 对手机用户来说，卡顿包含了很多场景，比如在 滑动列表的时候掉帧 、 应用启动白屏过长 、 点击电源键亮屏慢 、 界面操作没有反应然后闪退 、 点击图标没有响应 、 窗口动画不连贯、滑动不跟手、重启手机进入桌面卡顿 等场景，这些场景跟我们开发人员所理解的卡顿还有点不一样，开发人员会更加细分去分析这些问题，这是开发人员和用户之间的一个认知差异，这一点在处理用户(或者测试人员)的问题反馈的时候尤其需要注意 对开发人员来说，上面的场景包括了 流畅度 （滑动列表的时候掉帧、窗口动画不连贯、重启手机进入桌面卡顿）、 响应速…",
      "image": null,
      "publishedAt": "2021-04-24T11:55:02Z",
      "sourceId": "1aa1837ca33d8d55",
      "sourceTitle": "Android Performance",
      "link": "https://androidperformance.com/2021/04/24/android-systrace-smooth-in-action-1/",
      "detailPath": "articles/9fc20dd0d410c46aa5dee29b.json"
    },
    {
      "id": "df38399917d934153f79f3ab",
      "title": "前提",
      "summary": "提供一个直观的判断标准：我想写 100 个字，针对这 100 个字阅读量应该有 10000 字，吸收、处理、输出，一整套流程在经过训练之后，速度可以很快，甚至感觉像是直觉、不经意或者潜意识里完成了这份工作。 重点是，这 10000 字的阅读，是少不了的。很多时候我们阅读一段文本信息时，经常忽略了「前提」这个重要部分。一段话被随意摘录出来，可以供给给正反两方来用，大家都能找到支持自己观点的角度，问题就在这里，他们会刻意制造某种「前提」，让你从他们规划好的路径出发去思考。 不幸的是，大家很容易上套，奇葩说是一个很好的例子。我经常跟朋友说，看一个人说话，要看他没说什么，而不是说了什么。",
      "image": null,
      "publishedAt": "2021-04-22T00:00:00Z",
      "sourceId": "fc41292f8a54624e",
      "sourceTitle": "Elizen's Blog",
      "link": "https://elizen.me/posts/2021/04/qian-ti/",
      "detailPath": "articles/df38399917d934153f79f3ab.json"
    },
    {
      "id": "477d730c30a81eabea1f5eaa",
      "title": "谈谈 Kubernetes 的问题和局限性",
      "summary": "",
      "image": null,
      "publishedAt": "2021-04-16T00:00:00Z",
      "sourceId": "4d49716051922902",
      "sourceTitle": "面向信仰编程 - Articles",
      "link": "https://draven.co//kuberentes-limitations",
      "detailPath": "articles/477d730c30a81eabea1f5eaa.json"
    },
    {
      "id": "63d6dfe8c76c57ba9cf45c65",
      "title": "「Maven」IDEA下 Tomcat 10 Servlet 404 问题踩坑",
      "summary": "起因 下午将 Tomcat升级到了 10.0.4 版本，导致原先的 JSP Servlet 全部报了404。 搜寻了互联网，大部分都是配置 web.xml 的 metadata-complete 为 false ，但这样对于我的项目无效。 解决方案 IDEA 建立 Java Enterprise 工程，默认的Servlet API是 javax.servlet-api 的 4.0.1 版本 1 2 3 4 5 6 <dependency> <groupId> javax.servlet </groupId> <artifactId> javax.servlet-api </artifactId> <version> 4.0.1 </version> <scope> provided </scope> </de…",
      "image": "https://cdn.taurusxin.com/old-cdn/typecho/2021/04/12/404.png",
      "publishedAt": "2021-04-12T17:25:00Z",
      "sourceId": "3220115c042340a7",
      "sourceTitle": "TaurusXin 的独立博客",
      "link": "https://www.taurusxin.com/tomcat10-issue/",
      "detailPath": "articles/63d6dfe8c76c57ba9cf45c65.json"
    },
    {
      "id": "4589f24fa768c26d7de33b28",
      "title": "近期安全动态和点评（2021年1季度）",
      "summary": "又到了每季度的安全新闻汇总。今天这篇比较长，有些俺认为不那么重要的新闻，就没有放进来了。 ★隐私保护 ◇【输入法】的隐私风险 《 输入法会“背叛”我们吗？ @ 南方周末 》 一位受访者对南方周末记者描述，几天前朋友家要换马桶，她微信回信息说了自家用的牌子，下次打开手机 WPS 时，开屏广告就成了京东马桶。“这种 N 年不提的话题，不可能这么巧吧？”她怀疑是输入法泄密。 根据 Mob 研究院数据，2020年搜狗、讯飞和百度三家输入法占据了国内市场九成的活跃用户，其中搜狗占有率最高，54%。2020年9月，腾讯全资收购了搜狗。 易观一组数据表明，中国第三方输入法的活跃用户在2019年达到7.71亿。输入法已成网民刚需。 输入法会获取哪些信息 ...... 梳理三份隐私政策，输入法软件可能收集的用户信息有11类，涉…",
      "image": "https://lh5.googleusercontent.com/9nVxRF6BT2ff8C4B-HwtU4Kf9bluP-dGuhHtrNYVBjQ97Y6Zea_Vgxn03zmuxLS6wpEowQfLE2ZGA7s3gho_Xi7AcssZZGqw9XP_N_w_w8mWtPO7GDrLmGkIpF1wnXay5Q0wnyMnhyo=s72-c",
      "publishedAt": "2021-04-11T14:04:00Z",
      "sourceId": "92a77bfacd821259",
      "sourceTitle": "编程随想的博客",
      "link": "https://program-think.blogspot.com/2021/04/security-news.html",
      "detailPath": "articles/4589f24fa768c26d7de33b28.json"
    },
    {
      "id": "76805d2932c16bdcdc2f615a",
      "title": "为什么 Linux 和 macOS 不需要碎片整理",
      "summary": "",
      "image": null,
      "publishedAt": "2021-04-10T00:00:00Z",
      "sourceId": "4d49716051922902",
      "sourceTitle": "面向信仰编程 - Articles",
      "link": "https://draven.co//whys-the-design-linux-macos-fragmentation",
      "detailPath": "articles/76805d2932c16bdcdc2f615a.json"
    },
    {
      "id": "fd93dc9f5e9d7c5e6c122e16",
      "title": "CPU 和 GPU - 异构计算的演进与发展",
      "summary": "",
      "image": null,
      "publishedAt": "2021-04-09T00:00:00Z",
      "sourceId": "4d49716051922902",
      "sourceTitle": "面向信仰编程 - Articles",
      "link": "https://draven.co//heterogeneous-computing",
      "detailPath": "articles/fd93dc9f5e9d7c5e6c122e16.json"
    },
    {
      "id": "e6681df8261fac47f9d93234",
      "title": "Windows 技巧分享（三）常用软件01——生产力工具",
      "summary": "[scode type=“share”]这周末要搬家了哈~所以最近一段时间比较忙，因为在学校里，事情也比较多，主要就是忙企业的事情，这里是我的私人博客，也可以去我们公司的博客瞅一瞅，在左侧的友情链接或者是直接 戳这里 。 [/scode] 生产力之始 作为一个信息行业工作者，每天所要用到的生产力工具无数。开发工具，编辑器，IDE，命令行工具等等。 首先抛出一个问题。程序员装完一台电脑最先要安装的是什么？ 对我来说是 Chrome 当然，Windows 10 2004之后的版本，都将原先的内置旧版 Edge 换成了与 Google 合作的 Chromium 内核的 Microsoft Edge，体验大大增强。 很多人都说换到 Edge 有着十分优良的体验，确实很香，然而对于我来说，迁移数据真的是十分痛苦的一件事…",
      "image": "https://cdn.taurusxin.com/old-cdn/typecho/2021/04/22/Chrome.png",
      "publishedAt": "2021-04-07T17:47:00Z",
      "sourceId": "3220115c042340a7",
      "sourceTitle": "TaurusXin 的独立博客",
      "link": "https://www.taurusxin.com/windows-skill-03/",
      "detailPath": "articles/e6681df8261fac47f9d93234.json"
    }
  ]
}
