{
  "items": [
    {
      "id": "b4fd9725ae94272c42b52be0",
      "title": "脱离人生系统 一段时间后的感受",
      "summary": "脱离电脑工作、生活有一段时间了，日常工作我刻意不用电脑，只是在下班后我才会用电脑。当然，也就无法正常运转我的人生管理系统。 老读者都知道，我的人生管理系统构建在 Notion 上，这款软件非常庞大 […]",
      "image": "https://joojen.com/wp-content/uploads/2026/07/90460.png",
      "publishedAt": "2026-07-11T08:04:21Z",
      "sourceId": "917212a1b89654f9",
      "sourceTitle": "必须生猛--放羊心事2.0 » 必须生猛--放羊心事2.0",
      "link": "https://joojen.com/archives/9046.html",
      "detailPath": "articles/b4fd9725ae94272c42b52be0.json"
    },
    {
      "id": "443528c24f9fe8f8eb8bae11",
      "title": "日更是没用的",
      "summary": "刚才看了一下我的公众号，上一次更新竟然还是16号，也就是说，已经一周没更新了。 我经常读的几个写手，都是在日更，不是简单的长年累月，而是十来年这种时间长度。而每过两年，就会有一群新的读者和新的内容 […]",
      "image": "https://joojen.com/wp-content/uploads/2026/06/90400.png",
      "publishedAt": "2026-06-24T05:49:00Z",
      "sourceId": "917212a1b89654f9",
      "sourceTitle": "必须生猛--放羊心事2.0 » 必须生猛--放羊心事2.0",
      "link": "https://joojen.com/archives/9040.html",
      "detailPath": "articles/443528c24f9fe8f8eb8bae11.json"
    },
    {
      "id": "099f88c7d53a614b1706012b",
      "title": "2026年5月房地产数据来了",
      "summary": "今天，统计局正式发布了5月份的国民经济宏观数据，当然，也包含房地产行业的指数。 其中我经常看的就这几个数据，固定资产投资，房地产投资，以及70个中城市二手房价格指数。 从这几个数据来看，虽然4 […]",
      "image": "https://joojen.com/wp-content/uploads/2026/06/90340.png",
      "publishedAt": "2026-06-17T12:46:45Z",
      "sourceId": "917212a1b89654f9",
      "sourceTitle": "必须生猛--放羊心事2.0 » 必须生猛--放羊心事2.0",
      "link": "https://joojen.com/archives/9034.html",
      "detailPath": "articles/099f88c7d53a614b1706012b.json"
    },
    {
      "id": "3764971765563f3b0d64d7f9",
      "title": "大学生到技校回炉重造成为趋势",
      "summary": "又到一年毕业季，一千两百多万的大学毕业生，而整个社会能提供的岗位数量不过小几百万，这还都是把考研、直播、自媒体都算上后的。 可以想象一下，就业形势多么严峻。也意味着，很多大学毕业生，无法找到工作。 […]",
      "image": "https://joojen.com/wp-content/uploads/2026/06/90280.png",
      "publishedAt": "2026-06-17T12:45:32Z",
      "sourceId": "917212a1b89654f9",
      "sourceTitle": "必须生猛--放羊心事2.0 » 必须生猛--放羊心事2.0",
      "link": "https://joojen.com/archives/9028.html",
      "detailPath": "articles/3764971765563f3b0d64d7f9.json"
    },
    {
      "id": "44a398e62bccf8c275a45bce",
      "title": "你只是打个工而已",
      "summary": "钉钉内部的一篇7.5万字的离职感言《置身钉内》被广为流传，甚至流传到公司以外了。这是打工人的共情，更多人能够有身临其境的切身感受，职场文化的种种到处都是，只是大家经历的略有不同罢了。 和菜头老 […]",
      "image": "https://joojen.com/wp-content/uploads/2026/06/90220.png",
      "publishedAt": "2026-06-15T14:57:12Z",
      "sourceId": "917212a1b89654f9",
      "sourceTitle": "必须生猛--放羊心事2.0 » 必须生猛--放羊心事2.0",
      "link": "https://joojen.com/archives/9022.html",
      "detailPath": "articles/44a398e62bccf8c275a45bce.json"
    },
    {
      "id": "2bf1916ca0eed6625593d49b",
      "title": "关于工作本质的思考",
      "summary": "到现在也没能想清楚这个概念，一直以来，大家追求的无非是一份薪水，越高越好，逐年增加更好，用大量的时间和精力投入到其中，来换取生活的改善，甚至只能保持生活的位置。 站在上帝视角上，制定规则的人，不能 […]",
      "image": "https://joojen.com/wp-content/uploads/2026/06/90180.png",
      "publishedAt": "2026-06-12T10:06:41Z",
      "sourceId": "917212a1b89654f9",
      "sourceTitle": "必须生猛--放羊心事2.0 » 必须生猛--放羊心事2.0",
      "link": "https://joojen.com/archives/9018.html",
      "detailPath": "articles/2bf1916ca0eed6625593d49b.json"
    },
    {
      "id": "d55c7f78f1ec922ee8e76d1d",
      "title": "房子依然是很多人意难平",
      "summary": "周一那天一时兴起写了一篇关于房价的文章，顺便聊了一下新的「城市更新」政策内容。短短两天时间超过5万人阅读。 这样的文章被系统推荐让这么多人看到，已经说明了一点，当下，让房地产走出通缩周期是官方意志，或 […]",
      "image": "https://joojen.com/wp-content/uploads/2026/06/90120.png",
      "publishedAt": "2026-06-07T13:19:35Z",
      "sourceId": "917212a1b89654f9",
      "sourceTitle": "必须生猛--放羊心事2.0 » 必须生猛--放羊心事2.0",
      "link": "https://joojen.com/archives/9012.html",
      "detailPath": "articles/d55c7f78f1ec922ee8e76d1d.json"
    },
    {
      "id": "8e7d7db7b4559bdff800c2bb",
      "title": "写在高考前夜",
      "summary": "今天是个特殊的日子，2026年6月6日，又是周六，被称为666，本来以为今天高考，查了一下才知道明天才正式开始高考。 不过也好，今天这样的日子去熟悉考场，加上周末，家长们也能好好做做准备，为孩子保 […]",
      "image": "https://joojen.com/wp-content/uploads/2026/06/90150.png",
      "publishedAt": "2026-06-06T10:04:21Z",
      "sourceId": "917212a1b89654f9",
      "sourceTitle": "必须生猛--放羊心事2.0 » 必须生猛--放羊心事2.0",
      "link": "https://joojen.com/archives/9015.html",
      "detailPath": "articles/8e7d7db7b4559bdff800c2bb.json"
    },
    {
      "id": "1d4713728f79cf46e1df367e",
      "title": "房价又要起飞了？",
      "summary": "5月28日发布了「城市更新十五五规划」，不少人开始疯狂解读，认为这是十年前「货币化棚改」政策的翻版，至此，房价又将再次起飞。 这大概是渴太久了。 我更加确信的是，这可能是美好的愿景，如果这个政策能 […]",
      "image": "https://joojen.com/wp-content/uploads/2026/06/90030.png",
      "publishedAt": "2026-06-05T08:35:28Z",
      "sourceId": "917212a1b89654f9",
      "sourceTitle": "必须生猛--放羊心事2.0 » 必须生猛--放羊心事2.0",
      "link": "https://joojen.com/archives/9003.html",
      "detailPath": "articles/1d4713728f79cf46e1df367e.json"
    },
    {
      "id": "8d8ec0ded8f7a21f6896fffb",
      "title": "又到一年毕业季",
      "summary": "明天正式迈入6月份了，意味着毕业季，意味着就业季，虽然毕业季我写了很多年，但是这几年，每每聊这个话题的时候，都是负能量的东西偏多，因为大家都非常难。 现在反而比较好就业的，真的是那个手机开始拍短视 […]",
      "image": "https://joojen.com/wp-content/uploads/2026/06/90000.png",
      "publishedAt": "2026-06-01T04:06:36Z",
      "sourceId": "917212a1b89654f9",
      "sourceTitle": "必须生猛--放羊心事2.0 » 必须生猛--放羊心事2.0",
      "link": "https://joojen.com/archives/9000.html",
      "detailPath": "articles/8d8ec0ded8f7a21f6896fffb.json"
    },
    {
      "id": "9ad222588bdaa20360459109",
      "title": "为自己而工作",
      "summary": "最近正好在刷一本关注职场的书，书中访谈了十几位工作性质和经历都非常奇特的人，从gap这个概念入手，来剖析职场中的各种遭遇和可能的发展方向。 试图回答一个问题，你为谁而工作。 多数人在大公司里，经常 […]",
      "image": "https://joojen.com/wp-content/uploads/2026/05/89950.png",
      "publishedAt": "2026-05-29T13:11:41Z",
      "sourceId": "917212a1b89654f9",
      "sourceTitle": "必须生猛--放羊心事2.0 » 必须生猛--放羊心事2.0",
      "link": "https://joojen.com/archives/8995.html",
      "detailPath": "articles/9ad222588bdaa20360459109.json"
    },
    {
      "id": "a417df56ef68d08b20b9b567",
      "title": "允许一切发生，允许万物穿过自己",
      "summary": "长久以来，我自认为是个内耗型的人，容易自我加压、焦虑。同时希望去探索未知的时刻，不太愿意长时间被禁锢在一个环境中。即渴望稳定又心存对变化的追逐。 这正是自我内耗的结果，因为坚信人长时间在一个环境中 […]",
      "image": "https://joojen.com/wp-content/uploads/2026/05/89920.png",
      "publishedAt": "2026-05-25T02:33:08Z",
      "sourceId": "917212a1b89654f9",
      "sourceTitle": "必须生猛--放羊心事2.0 » 必须生猛--放羊心事2.0",
      "link": "https://joojen.com/archives/8992.html",
      "detailPath": "articles/a417df56ef68d08b20b9b567.json"
    },
    {
      "id": "6e8057043860729143f2890f",
      "title": "强调吃苦并不是什么好事情",
      "summary": "人无论是在工作还是学习阶段，容易被困在一个封闭的地方很长时间，这对于一个人来说不是什么好事情，得学会自我调节，都说人挪活树挪死，人不能长时间在一个地方焊死。 抽离一下或许是个好办法，一般被困在一个 […]",
      "image": "https://joojen.com/wp-content/uploads/2026/05/89890.png",
      "publishedAt": "2026-05-24T02:59:00Z",
      "sourceId": "917212a1b89654f9",
      "sourceTitle": "必须生猛--放羊心事2.0 » 必须生猛--放羊心事2.0",
      "link": "https://joojen.com/archives/8989.html",
      "detailPath": "articles/6e8057043860729143f2890f.json"
    },
    {
      "id": "8fd5c16a1e5d47b8fa96704d",
      "title": "为什么必须戒短视频",
      "summary": "现在似乎人人都打响了和刷短视频的一场自我战争。 因为都意识到这玩意不仅上瘾，而且刷着刷着半个小时就过去了、一个小时就过去了。 而在更要命的是，刷的时候挺爽，刷完之后，一种莫名的虚无感从心中升起。 […]",
      "image": "https://joojen.com/wp-content/uploads/2026/05/89860.png",
      "publishedAt": "2026-05-23T06:01:25Z",
      "sourceId": "917212a1b89654f9",
      "sourceTitle": "必须生猛--放羊心事2.0 » 必须生猛--放羊心事2.0",
      "link": "https://joojen.com/archives/8986.html",
      "detailPath": "articles/8fd5c16a1e5d47b8fa96704d.json"
    },
    {
      "id": "6f817e5c1f159862b939dbaf",
      "title": "2026年4月房地产数据来了",
      "summary": "五月过半，终于等来了四月份的房地产数据，从宏观投资上来看，跌幅再次加大，本来以为已经转向了，但是现在看来还为时过早，短期内看不到转正的希望。这种反复非常折腾人，经济也经不起这种折腾。 目前房地产的 […]",
      "image": "https://joojen.com/wp-content/uploads/2026/05/89790.png",
      "publishedAt": "2026-05-21T09:55:38Z",
      "sourceId": "917212a1b89654f9",
      "sourceTitle": "必须生猛--放羊心事2.0 » 必须生猛--放羊心事2.0",
      "link": "https://joojen.com/archives/8979.html",
      "detailPath": "articles/6f817e5c1f159862b939dbaf.json"
    }
  ]
}
