{
  "id": "2afc507e1f493751e525b59a",
  "title": "2026 万事皆可期",
  "summary": "祝大家心有所悦，业有所成，万事皆可期！愿你如翠柏般舒展，怀拥蓝天的开阔；似小花般明媚，攒满日常的欢喜；随蕨叶沐光，把每段时光都过成暖色调的诗。",
  "content": "<p><img src=\"https://yayu.net/wp-content/uploads/2026/01/2026010104401047.webp\" alt=\"\" width=\"1500\" height=\"1001\"></p>\n<p><img src=\"https://yayu.net/wp-content/uploads/2026/01/2026010104401152.webp\" alt=\"\" width=\"1500\" height=\"1001\"></p>\n<p><img src=\"https://yayu.net/wp-content/uploads/2026/01/202601010440114.webp\" alt=\"\" width=\"1500\" height=\"1001\"></p>\n<p>祝大家心有所悦，业有所成，万事皆可期！</p>\n<p>愿你如翠柏般舒展，怀拥蓝天的开阔；似小花般明媚，攒满日常的欢喜；随蕨叶沐光，把每段时光都过成暖色调的诗。</p>",
  "image": "https://yayu.net/wp-content/uploads/2026/01/2026010104401047.webp",
  "publishedAt": "2026-01-01T04:45:32Z",
  "sourceId": "d97698cb61c165ac",
  "sourceTitle": "雅余  ·  茶余饭后，闲情雅致",
  "link": "https://yayu.net/6081.html"
}
