{
  "id": "3790f4876a1100aadc71e815",
  "title": "Can Debezium Lose Events?",
  "summary": "This question came up on the Data Engineering sub-reddit the other day: Can Debezium lose any events ? I.e. can there be a situation where a record in a database get inserted, updated, or deleted, but Debezium fails to capture that event from the transaction log and propagate it to downstream consumers?",
  "content": "<div>\n<p>This question came up on the Data Engineering sub-reddit the other day:\n<a href=\"https://old.reddit.com/r/dataengineering/comments/17ttw5e/can_debezium_loose_updates/\" target=\"_blank\" rel=\"noopener noreferrer\">Can Debezium lose any events</a>?\nI.e. can there be a situation where a record in a database get inserted, updated, or deleted, but Debezium fails to capture that event from the transaction log and propagate it to downstream consumers?</p>\n</div>",
  "image": null,
  "publishedAt": "2023-11-14T14:00:00Z",
  "sourceId": "d159169f81b06175",
  "sourceTitle": "morling.dev -- Blog",
  "link": "https://www.morling.dev/blog/can-debezium-lose-events/"
}
