{
  "id": "9b69d189af8c67d484db3fad",
  "title": "无标题文章",
  "summary": "RE: https:// mastodon.gamedev.place/@Fronko nGames/116891600419803302 the hell, this is worse then the initial reports suggested, more than 70% of id Software gone damn, what a bloodbath.",
  "content": "<p>RE: <a href=\"https://mastodon.gamedev.place/@FronkonGames/116891600419803302\" target=\"_blank\" rel=\"noopener noreferrer\"><span>https://</span><span>mastodon.gamedev.place/@Fronko</span><span>nGames/116891600419803302</span></a></p><p>the hell, this is worse then the initial reports suggested, more than 70% of id Software gone damn, what a bloodbath.</p>",
  "image": null,
  "publishedAt": "2026-07-09T19:14:59Z",
  "sourceId": "9b2c31dc7bab3335",
  "sourceTitle": "David Amador",
  "link": "https://mastodon.gamedev.place/@djlink/116891615223395254"
}
