{
  "id": "d8f8495ee65687574eb539b4",
  "title": "sum-grid.love",
  "summary": "A little sudoku-like app for helping first-graders practice addition. This attempt at situated software for schooling got a little more use than spell-cards.love . video; 25 seconds",
  "content": "<p>\n<a href=\"https://git.sr.ht/~akkartik/sum-grid.love\" target=\"_blank\" rel=\"noopener noreferrer\">A little sudoku-like app\nfor helping first-graders practice addition.</a> This attempt at situated\nsoftware for schooling got a little more use than <a href=\"https://akkartik.name/post/spell-cards\" target=\"_blank\" rel=\"noopener noreferrer\">spell-cards.love</a>.\n\n<p>\n<a href=\"https://akkartik.name/images/20231116-sum-grid-fixed.webm\" target=\"_blank\" rel=\"noopener noreferrer\">\n  \n    \n  \n</a>\n<div>\n  video; 25 seconds\n</div>",
  "image": null,
  "publishedAt": "2023-11-16T07:00:00Z",
  "sourceId": "02d1f8c50af2caba",
  "sourceTitle": "Kartik Agaram",
  "link": "http://akkartik.name/post/sum-grid"
}
