{
  "id": "f3edf7f7d3a21dfc78830b5d",
  "title": "无标题文章",
  "summary": "It's absolutely shocking that German restaurants can hire lawyers to make Google take down any local reviews that aren't 5 stars. I've had a take-down notice for a 3-star review for what was a fairly average burger place. I could try to contest it, but without going to court it would likely amount to nothing. Don't believe Google Maps ratings in Germany.",
  "content": "<p>It&#x27;s absolutely shocking that German restaurants can hire lawyers to make Google take down any local reviews that aren&#x27;t 5 stars.</p><p>I&#x27;ve had a take-down notice for a 3-star review for what was a fairly average burger place. I could try to contest it, but without going to court it would likely amount to nothing.</p><p>Don&#x27;t believe Google Maps ratings in Germany.</p>",
  "image": null,
  "publishedAt": "2024-11-26T13:10:44Z",
  "sourceId": "c4e271ba9b43cc74",
  "sourceTitle": "Ash Davies",
  "link": "https://androiddev.social/@ashdavies/113549419751207618"
}
