{
  "id": "f80d42c3e8b9e9a47419126f",
  "title": "无标题文章",
  "summary": "Lots of \"I built this with AI\" posts lately. Here's one where I actually enjoyed the building part. Introducing PodSync (for editors): a podcast alignment tool (uses VAD, MFCC fingerprinting, x-correlation). AI helped me 👨‍💻 it in Rust but yrs of aligning tracks 👂helped with the algo! Wrote up the full approach with an interactive demo: - https:// kau.sh/bl…",
  "content": "nonadult",
  "image": "https://media.hachyderm.io/media_attachments/files/116/257/266/150/154/393/original/9cb1b30554d9c7ea.webp",
  "publishedAt": "2026-03-20T13:13:49Z",
  "sourceId": "44d2bdb6054f3121",
  "sourceTitle": "Kaushik Gopal",
  "link": "https://hachyderm.io/@kaush/116261678561161550"
}
