{
  "id": "fdfd69dda2966d141fbb1c5c",
  "title": "Linux 用作 IPv6 网关",
  "summary": "IPv6作为下一代互联网的核心技术，拥有众多新特性和优势，不仅解决了IPv4网络地址T 量不够的问题，还一并解决了很多其他问题。 本文将集中讨论在西电校园网环境下，将Linux PC作为IPv6网关，让局域网可以正常接入IPv6网络的解决方案。 网络结构 本文中的网络结构如下： 2001:250:1006:6151::1/64 +--------+ +---------+ | 校园网 | eth0 | Linux | | +---------------+ 局域网 | | 网关 | | 网关 | +--------+ +----+----+ | eth1 +--------+--------+ +---+--------+--------+---+ | +-+-+ +-+-+ +-+-+ | | | | |…",
  "content": "<p>IPv6作为下一代互联网的核心技术，拥有众多新特性和优势，不仅解决了IPv4网络地址T 量不够的问题，还一并解决了很多其他问题。\n本文将集中讨论在西电校园网环境下，将Linux PC作为IPv6网关，让局域网可以正常接入IPv6网络的解决方案。</p>\n<h2>网络结构</h2>\n<p>本文中的网络结构如下：</p>\n<pre>\n<code>\n2001:250:1006:6151::1/64\n     +--------+               +---------+ \n     | 校园网  |          eth0 |  Linux  | \n     |        +---------------+  局域网  | \n     |  网关   |               |  网关    | \n     +--------+               +----+----+ \n                                   | eth1\n                          +--------+--------+\n                      +---+--------+--------+---+ \n                      | +-+-+    +-+-+    +-+-+ | \n                      | |   |    |   |    |   | | \n                      | |   |    |   |    |   | | \n                      | +---+    +---+    +---+ | \n                      |      局   域   网        | \n                      +-------------------------+ \n</code>\n</pre>",
  "image": null,
  "publishedAt": "2011-11-25T00:00:00Z",
  "sourceId": "1a53726dacd05db7",
  "sourceTitle": "K.I.S.S",
  "link": "https://bigeagle.me/2011/11/linux-as-ipv6-gateway/"
}
